scsd/__init__.py
scsd/ellipsoid.py
scsd/kingsbury_id_au_webserver.py
scsd/make_smarts.py
scsd/nsd.py
scsd/refresh_dfs.py
scsd/scsd.py
scsd/scsd_build_tools.py
scsd/scsd_models.json
scsd/scsd_models.py
scsd/scsd_models_user.py
scsd/scsd_single_cl.py
scsd/scsd_symmetry.py
scsd/scsd_webserver.py
scsd/data/nsd_202203.pkl
scsd/data/scsd/blue box_scsd_20220719.pkl
scsd/data/scsd/combined_df.pkl
scsd/data/scsd/corrole_scsd_20230816.pkl
scsd/data/scsd/porphycene_scsd_20220713.pkl
scsd/data/scsd/porphycene_scsd_20231020.pkl
scsd/data/scsd/porphyrin_scsd_20220713.pkl
scsd/data/scsd/porphyrin_scsd_20230615.pkl
scsd/data/scsd/scsd_models_user.py
scsd/data/scsd/scsd_structure_refcodes.html
scsd/data/scsd/texaphyrin_scsd_20231019.pkl
scsd/data/scsd/ttf_scsd_20220713.pkl
scsd/data/scsd/xanthene_scsd_20220713.pkl
scsd/static/coord_table_ref_str_mat.html
scsd/static/scsd_structure_refcodes.html
scsd/templates/scsd/pca_overall.html
scsd/templates/scsd/pca_row.html
scsd/templates/scsd/scsd_bodipy_custom.html
scsd/templates/scsd/scsd_compare_table.html
scsd/templates/scsd/scsd_hidden_raw_data_section.html
scsd/templates/scsd/scsd_html_template.html
scsd/templates/scsd/scsd_html_template_v2.html
scsd/templates/scsd/scsd_html_template_v3.html
scsd/templates/scsd/scsd_model_report.html
scsd/templates/scsd/scsd_models_table.html
scsd/templates/scsd/scsd_uploader.html
scsd/templates/scsd/scsd_uploader_ccdc.html
scsd/templates/scsd/scsd_uploader_localtest.html
scsd/templates/scsd/scsd_uploader_new_model.html
scsd/templates/scsd/scsd_uploader_new_model_local.html
scsd/templates/scsd/xtal_table_output.html
scsd/templates/scsd/xtal_table_uploader.html
scsdpy-0.1.1.dist-info/LICENSE
scsdpy-0.1.1.dist-info/METADATA
scsdpy-0.1.1.dist-info/WHEEL
scsdpy-0.1.1.dist-info/top_level.txt
scsdpy-0.1.1.dist-info/RECORD
