Metadata-Version: 2.1
Name: scsdpy
Version: 0.1.1
Summary: SCSD is Python software for the analysis of molecular conformation and deformation in crystal structures
Home-page: https://github.com/cjkingsbury/scsd
Author: Dr Christopher Kingsbury
Author-email: ckingsbury@ccdc.cam.ac.uk
License: ANTI-1.4
Platform: linux
Platform: windows
Platform: osx
Platform: win32
Classifier: Programming Language :: Python :: 3
Classifier: Operating System :: OS Independent
License-File: LICENSE
Requires-Dist: numpy >=1.16.2
Requires-Dist: pandas >=0.23.4
Requires-Dist: scipy >=1.4.1
Requires-Dist: plotly >=5.1.2
Requires-Dist: flask >=1.1.2
Requires-Dist: scikit-learn >=0.24.2
Requires-Dist: networkx >=2.2
Requires-Dist: matplotlib >=3.2.2
Requires-Dist: seaborn >=0.11.1
Requires-Dist: werkzeug >=3.0.3
